ablate/__init__.py
ablate/py.typed
ablate/report.py
ablate/blocks/__init__.py
ablate/blocks/abstract_block.py
ablate/blocks/figure_blocks.py
ablate/blocks/table_blocks.py
ablate/blocks/text_blocks.py
ablate/core/__init__.py
ablate/core/types/__init__.py
ablate/core/types/runs.py
ablate/exporters/__init__.py
ablate/exporters/abstract_exporter.py
ablate/exporters/markdown_exporter.py
ablate/exporters/notebook_exporter.py
ablate/exporters/utils.py
ablate/queries/__init__.py
ablate/queries/grouped_query.py
ablate/queries/query.py
ablate/queries/selectors.py
ablate/sources/__init__.py
ablate/sources/abstract_source.py
ablate/sources/autrainer_source.py
ablate/sources/clearml_source.py
ablate/sources/mlflow_source.py
ablate/sources/mock_source.py
ablate/sources/tensorboard_source.py
ablate/sources/wandb_source.py
ablate-0.2.3.dist-info/METADATA
ablate-0.2.3.dist-info/WHEEL
ablate-0.2.3.dist-info/licenses/LICENSE
ablate-0.2.3.dist-info/RECORD
