Metadata-Version: 2.4
Name: ablate
Version: 0.2.3
Summary: ablate turns deep learning experiments into structured, human-readable reports.
Author-email: Simon Rampp <simon@rampp.dev>
License: MIT
License-File: LICENSE
Keywords: deep learning,experiment tracking,machine learning,markdown,reporting
Classifier: Operating System :: OS Independent
Classifier: Programming Language :: Python :: 3
Classifier: Programming Language :: Python :: 3.10
Classifier: Programming Language :: Python :: 3.11
Classifier: Programming Language :: Python :: 3.12
Classifier: Programming Language :: Python :: 3.13
Requires-Python: >=3.10
Requires-Dist: matplotlib>=3.10.3
Requires-Dist: pandas>=2.2.3
Requires-Dist: pydantic>=2.11.4
Requires-Dist: pyyaml>=6.0.2
Requires-Dist: seaborn>=0.13.2
Requires-Dist: tabulate>=0.9.0
Provides-Extra: clearml
Requires-Dist: clearml>=2.0.0; extra == 'clearml'
Provides-Extra: jupyter
Requires-Dist: jupyter>=1.1.1; extra == 'jupyter'
Provides-Extra: mlflow
Requires-Dist: mlflow>=2.22.0; extra == 'mlflow'
Provides-Extra: tensorboard
Requires-Dist: tensorboard>=2.19.0; extra == 'tensorboard'
Provides-Extra: wandb
Requires-Dist: wandb>=0.19.11; extra == 'wandb'
